networkkit/.gitignore
networkkit/__init.py__
networkkit/databus.py
networkkit/messages.py
networkkit/network.py
networkkit-0.0.1.dist-info/METADATA
networkkit-0.0.1.dist-info/WHEEL
networkkit-0.0.1.dist-info/licenses/LICENSE
networkkit-0.0.1.dist-info/RECORD
