Metadata-Version: 2.3
Name: networkkit
Version: 0.0.1
Summary: A simple communication framework for agents using pubsub and http
Project-URL: Repository, https://github.com/japanvik/networkkit
Author-email: Vikram Kumar <vik@japanvik.net>
License:                                  Apache License
License-File: LICENSE
Keywords: communication,framework,network agents,pubsub
Classifier: Development Status :: 4 - Beta
Classifier: Programming Language :: Python
Requires-Python: >=3.8
Requires-Dist: fastapi
Requires-Dist: pydantic
Requires-Dist: requests
Requires-Dist: uvicorn
Requires-Dist: zmq
